setup.cfg
setup.py
django_lookup.egg-info/PKG-INFO
django_lookup.egg-info/SOURCES.txt
django_lookup.egg-info/dependency_links.txt
django_lookup.egg-info/pbr.json
django_lookup.egg-info/requires.txt
django_lookup.egg-info/top_level.txt
lookup/__init__.py
lookup/domain.py
lookup/legacy.py
lookup/models.py
lookup/management/__init__.py
lookup/management/commands/__init__.py
lookup/management/commands/lookup_clean.py
lookup/management/commands/lookup_init.py
lookup/migrations/0001_initial.py
lookup/migrations/__init__.py
test/__init__.py
test/factories.py
test/settings.py
test/test_domain.py
test/testapp/__init__.py
test/testapp/models.py