Metadata-Version: 1.1
Name: django-lookup
Version: 0.0.1
Summary: Lookup tables for Django models with management features and fuzzy matching
Home-page: https://github.com/Unholster/django-lookup
Author: Sebastián Acuña
Author-email: sebastian@unholster.com
License: MIT License
Platform: UNKNOWN
Classifier: Development Status :: 5 - Production/Stable
Classifier: Topic :: Utilities
